README.txt
setup.py
adaptor/__init__.py
adaptor/fields.py
adaptor/model.py
django_adaptors.egg-info/PKG-INFO
django_adaptors.egg-info/SOURCES.txt
django_adaptors.egg-info/dependency_links.txt
django_adaptors.egg-info/requires.txt
django_adaptors.egg-info/top_level.txt