Metadata-Version: 1.1
Name: django-adaptors
Version: 0.2.1.0
Summary: Convert CSV/XML files into python object or django model
Home-page: UNKNOWN
Author: Anthony Tresontani
Author-email: dev.tresontani@gmail.com
License: BSD
Keywords: CSV XML Django adaptor
Platform: UNKNOWN
Classifier: Development Status :: 3 - Alpha
Classifier: Topic :: Utilities
Classifier: License :: OSI Approved :: BSD License
